ktu/__init__.py
ktu/scheme.py
ktu-0.0.1.dist-info/LICENSE
ktu-0.0.1.dist-info/METADATA
ktu-0.0.1.dist-info/WHEEL
ktu-0.0.1.dist-info/top_level.txt
ktu-0.0.1.dist-info/RECORD
