Metadata-Version: 2.1
Name: ktu
Version: 0.0.1
Summary: A Python package to get ktu stuffs
Author-email: Don Sabu <donsabu@protonmail.com>
Project-URL: Source, https://github.com/ad_sjcet
Keywords: ktu
Requires-Python: >=3.7
License-File: LICENSE
